kfputils/__init__.py
kfputils/aws.py
kfputils/client.py
kfputils/kfputils.py
kfputils/pipeline.py
kfputils/pipeline_cli.py
kfputils/run.py
kfputils/run_cli.py
kfputils/uploadrun.py
kfputils/utils.py
kfputils-0.4.11.dist-info/LICENSE
kfputils-0.4.11.dist-info/METADATA
kfputils-0.4.11.dist-info/WHEEL
kfputils-0.4.11.dist-info/entry_points.txt
kfputils-0.4.11.dist-info/top_level.txt
kfputils-0.4.11.dist-info/RECORD
