Metadata-Version: 2.1
Name: kfputils
Version: 0.4.11
Summary: Kubeflow pipeline utils
Home-page: https://github.com/cloudxlr8r/kfputils
Author: Cloud XLR8R
Author-email: hello@cloudxlr8r.com
License: MIT
Platform: UNKNOWN
Classifier: Development Status :: 5 - Production/Stable
Classifier: Natural Language :: English
Classifier: License :: OSI Approved :: MIT License
Classifier: Operating System :: OS Independent
Classifier: Programming Language :: Python
Classifier: Programming Language :: Python :: 3
Classifier: Programming Language :: Python :: 3.10
License-File: LICENSE
Requires-Dist: kfp (==1.8.10)
Requires-Dist: click (==8.0.3)
Requires-Dist: pyyaml (==5.4.1)
Requires-Dist: typing-extensions (==3.10.0.2)
